pastlogging/__init__.py
pastlogging-1.0a1.dist-info/LICENSE
pastlogging-1.0a1.dist-info/METADATA
pastlogging-1.0a1.dist-info/WHEEL
pastlogging-1.0a1.dist-info/top_level.txt
pastlogging-1.0a1.dist-info/RECORD
