Metadata-Version: 2.1
Name: pastlogging
Version: 1.0a1
Summary: Logging extension to emit full logs when a threshold is reached
Home-page: https://github.com/jimstraus/pastlogging
Author: Jim Straus
Author-email: jims@keymail.com
License: UNKNOWN
Keywords: logging
Platform: UNKNOWN
Classifier: Development Status :: 3 - Alpha
Classifier: Intended Audience :: Developers
Classifier: License :: OSI Approved :: MIT License
Classifier: Programming Language :: Python :: 3
Classifier: Programming Language :: Python :: 3.4
Classifier: Programming Language :: Python :: 3.5
Classifier: Programming Language :: Python :: 3.6
Classifier: Programming Language :: Python :: 3.7
Provides-Extra: dev
Requires-Dist: check-manifest ; extra == 'dev'
Provides-Extra: test
Requires-Dist: pytest ; extra == 'test'
Requires-Dist: pytest-cover ; extra == 'test'
